autoskinning/__init__.py
autoskinning/core.py
autoskinning-0.1.dist-info/METADATA
autoskinning-0.1.dist-info/WHEEL
autoskinning-0.1.dist-info/entry_points.txt
autoskinning-0.1.dist-info/top_level.txt
autoskinning-0.1.dist-info/RECORD
