Metadata-Version: 2.1
Name: autoskinning
Version: 0.1
Summary: tool for autoskinning
Home-page: https://github.com/project/autoskinning
Author: beanliu
Classifier: Programming Language :: Python :: 3
Classifier: Programming Language :: Python :: 2
Classifier: Operating System :: OS Independent
